{
  "sources": [
    {
      "file": "morph/data.csv",
      "create": {
        "type": "morph",
        "scraper": "tmtmtmtm/mozambique-assembleia",
        "query": "SELECT * FROM data"
      },
      "source": "https://morph.io/tmtmtmtm/mozambique-assembleia",
      "type": "membership"
    },
    {
      "file": "morph/terms.csv",
      "type": "term",
      "create": {
        "file": "morph/terms.csv",
        "type": "morph",
        "scraper": "tmtmtmtm/mozambique-assembleia",
        "query": "SELECT * FROM terms"
      }
    }
  ]
}