{
  "persons": [
    {
      "id": "person/alain_gros-desormeaux",
      "name": "Alain Gros-Desormeaux",
      "sources": [
        {
          "url": "https://fr.wikipedia.org/wiki/Conseil_territorial_de_Saint-Martin#Composition_du_conseil_territorial"
        }
      ]
    },
    {
      "birth_date": "1949-10-09",
      "gender": "female",
      "given_name": "Aline",
      "id": "person/Q16267497",
      "name": "Aline Hanson",
      "other_names": [
        {
          "lang": "fr",
          "name": "Aline Hanson",
          "note": "multilingual"
        },
        {
          "lang": "en",
          "name": "Aline Hanson",
          "note": "multilingual"
        },
        {
          "lang": "it",
          "name": "Aline Hanson",
          "note": "multilingual"
        },
        {
          "lang": "pl",
          "name": "Aline Hanson",
          "note": "multilingual"
        }
      ],
      "sources": [
        {
          "url": "https://fr.wikipedia.org/wiki/Conseil_territorial_de_Saint-Martin#Composition_du_conseil_territorial"
        }
      ]
    },
    {
      "id": "person/antero_santos",
      "name": "Antero Santos",
      "sources": [
        {
          "url": "https://fr.wikipedia.org/wiki/Conseil_territorial_de_Saint-Martin#Composition_du_conseil_territorial"
        }
      ]
    },
    {
      "id": "person/christophe_henocq",
      "name": "Christophe Henocq",
      "sources": [
        {
          "url": "https://fr.wikipedia.org/wiki/Conseil_territorial_de_Saint-Martin#Composition_du_conseil_territorial"
        }
      ]
    },
    {
      "id": "person/claire_manuel-philips",
      "name": "Claire Manuel-Philips",
      "sources": [
        {
          "url": "https://fr.wikipedia.org/wiki/Conseil_territorial_de_Saint-Martin#Composition_du_conseil_territorial"
        }
      ]
    },
    {
      "birth_date": "1968-01-08",
      "gender": "male",
      "given_name": "Daniel",
      "id": "person/Q4556137",
      "identifiers": [
        {
          "identifier": "310685375",
          "scheme": "viaf"
        },
        {
          "identifier": "18433",
          "scheme": "sycomore"
        }
      ],
      "links": [
        {
          "note": "facebook",
          "url": "334151066605825"
        },
        {
          "note": "website",
          "url": "http://deputation.danielgibbs.fr/"
        }
      ],
      "name": "Daniel Gibbs",
      "other_names": [
        {
          "lang": "fr",
          "name": "Daniel Gibbs",
          "note": "multilingual"
        },
        {
          "lang": "en",
          "name": "Daniel Gibbs",
          "note": "multilingual"
        },
        {
          "lang": "pl",
          "name": "Daniel Gibbs",
          "note": "multilingual"
        },
        {
          "lang": "es",
          "name": "Daniel Gibbes",
          "note": "multilingual"
        },
        {
          "lang": "nl",
          "name": "Daniel Gibbs",
          "note": "multilingual"
        },
        {
          "lang": "de",
          "name": "Daniel Gibbs",
          "note": "multilingual"
        },
        {
          "lang": "nb",
          "name": "Daniel Gibbs",
          "note": "multilingual"
        },
        {
          "lang": "da",
          "name": "Daniel Gibbs",
          "note": "multilingual"
        },
        {
          "lang": "nn",
          "name": "Daniel Gibbs",
          "note": "multilingual"
        },
        {
          "lang": "sv",
          "name": "Daniel Gibbs",
          "note": "multilingual"
        }
      ],
      "sources": [
        {
          "url": "https://fr.wikipedia.org/wiki/Conseil_territorial_de_Saint-Martin#Composition_du_conseil_territorial"
        }
      ]
    },
    {
      "id": "person/dominique_aubert",
      "name": "Dominique Aubert",
      "sources": [
        {
          "url": "https://fr.wikipedia.org/wiki/Conseil_territorial_de_Saint-Martin#Composition_du_conseil_territorial"
        }
      ]
    },
    {
      "birth_date": "1958-01-20",
      "gender": "male",
      "given_name": "Guillaume",
      "id": "person/Q3119642",
      "identifiers": [
        {
          "identifier": "senateur/arnell_guillaume14261s",
          "scheme": "senatdotfr"
        }
      ],
      "image": "https://upload.wikimedia.org/wikipedia/commons/3/3a/Guillaume_Arnell_2.jpg",
      "images": [
        {
          "url": "https://upload.wikimedia.org/wikipedia/commons/3/3a/Guillaume_Arnell_2.jpg"
        }
      ],
      "name": "Guillaume Arnell",
      "other_names": [
        {
          "lang": "fr",
          "name": "Guillaume Arnell",
          "note": "multilingual"
        },
        {
          "lang": "en",
          "name": "Guillaume Arnell",
          "note": "multilingual"
        },
        {
          "lang": "it",
          "name": "Guillaume Arnell",
          "note": "multilingual"
        }
      ],
      "sources": [
        {
          "url": "https://fr.wikipedia.org/wiki/Conseil_territorial_de_Saint-Martin#Composition_du_conseil_territorial"
        }
      ]
    },
    {
      "id": "person/jean-david_richardson",
      "name": "Jean-David Richardson",
      "sources": [
        {
          "url": "https://fr.wikipedia.org/wiki/Conseil_territorial_de_Saint-Martin#Composition_du_conseil_territorial"
        }
      ]
    },
    {
      "id": "person/jean-philippe_richardson",
      "name": "Jean-Philippe Richardson",
      "sources": [
        {
          "url": "https://fr.wikipedia.org/wiki/Conseil_territorial_de_Saint-Martin#Composition_du_conseil_territorial"
        }
      ]
    },
    {
      "id": "person/jeanne_rogers-vanterpool",
      "name": "Jeanne Rogers-Vanterpool",
      "sources": [
        {
          "url": "https://fr.wikipedia.org/wiki/Conseil_territorial_de_Saint-Martin#Composition_du_conseil_territorial"
        }
      ]
    },
    {
      "id": "person/josiane_carty-nettleford",
      "name": "Josiane Carty-Nettleford",
      "sources": [
        {
          "url": "https://fr.wikipedia.org/wiki/Conseil_territorial_de_Saint-Martin#Composition_du_conseil_territorial"
        }
      ]
    },
    {
      "id": "person/josé_vilier",
      "name": "José Vilier",
      "sources": [
        {
          "url": "https://fr.wikipedia.org/wiki/Conseil_territorial_de_Saint-Martin#Composition_du_conseil_territorial"
        }
      ]
    },
    {
      "id": "person/jules_charville",
      "name": "Jules Charville",
      "sources": [
        {
          "url": "https://fr.wikipedia.org/wiki/Conseil_territorial_de_Saint-Martin#Composition_du_conseil_territorial"
        }
      ]
    },
    {
      "id": "person/louis_fleming",
      "name": "Louis Fleming",
      "sources": [
        {
          "url": "https://fr.wikipedia.org/wiki/Conseil_territorial_de_Saint-Martin#Composition_du_conseil_territorial"
        }
      ]
    },
    {
      "id": "person/maud_ascent-gibbs",
      "name": "Maud Ascent-Gibbs",
      "sources": [
        {
          "url": "https://fr.wikipedia.org/wiki/Conseil_territorial_de_Saint-Martin#Composition_du_conseil_territorial"
        }
      ]
    },
    {
      "id": "person/nadine_jermin-paines",
      "name": "Nadine Jermin-Paines",
      "sources": [
        {
          "url": "https://fr.wikipedia.org/wiki/Conseil_territorial_de_Saint-Martin#Composition_du_conseil_territorial"
        }
      ]
    },
    {
      "id": "person/ramona_connor",
      "name": "Ramona Connor",
      "sources": [
        {
          "url": "https://fr.wikipedia.org/wiki/Conseil_territorial_de_Saint-Martin#Composition_du_conseil_territorial"
        }
      ]
    },
    {
      "id": "person/rené-jean_duret",
      "name": "René-Jean Duret",
      "sources": [
        {
          "url": "https://fr.wikipedia.org/wiki/Conseil_territorial_de_Saint-Martin#Composition_du_conseil_territorial"
        }
      ]
    },
    {
      "id": "person/rolande_questel",
      "name": "Rolande Questel",
      "sources": [
        {
          "url": "https://fr.wikipedia.org/wiki/Conseil_territorial_de_Saint-Martin#Composition_du_conseil_territorial"
        }
      ]
    },
    {
      "id": "person/rosette_gumbs-lake",
      "name": "Rosette Gumbs-Lake",
      "sources": [
        {
          "url": "https://fr.wikipedia.org/wiki/Conseil_territorial_de_Saint-Martin#Composition_du_conseil_territorial"
        }
      ]
    },
    {
      "id": "person/valérie_picotin-fontrose",
      "name": "Valérie Picotin-Fontrose",
      "sources": [
        {
          "url": "https://fr.wikipedia.org/wiki/Conseil_territorial_de_Saint-Martin#Composition_du_conseil_territorial"
        }
      ]
    },
    {
      "id": "person/wendel_cocks",
      "name": "Wendel Cocks",
      "sources": [
        {
          "url": "https://fr.wikipedia.org/wiki/Conseil_territorial_de_Saint-Martin#Composition_du_conseil_territorial"
        }
      ]
    }
  ],
  "organizations": [
    {
      "classification": "party",
      "id": "party/rassemblement_responsabilité_réussite",
      "name": "Rassemblement Responsabilité Réussite"
    },
    {
      "classification": "party",
      "id": "party/team_daniel_gibbs_2012",
      "name": "Team Daniel Gibbs 2012"
    },
    {
      "classification": "legislature",
      "id": "legislature",
      "identifiers": [
        {
          "identifier": "Q2994334",
          "scheme": "wikidata"
        }
      ],
      "name": "Territorial Council",
      "seats": 23
    }
  ],
  "meta": {
    "sources": [
      "https://fr.wikipedia.org/wiki/Conseil_territorial_de_Saint-Martin"
    ]
  },
  "memberships": [
    {
      "legislative_period_id": "term/2012",
      "on_behalf_of_id": "party/rassemblement_responsabilité_réussite",
      "organization_id": "legislature",
      "person_id": "person/Q16267497",
      "role": "member"
    },
    {
      "legislative_period_id": "term/2012",
      "on_behalf_of_id": "party/rassemblement_responsabilité_réussite",
      "organization_id": "legislature",
      "person_id": "person/Q3119642",
      "role": "member"
    },
    {
      "legislative_period_id": "term/2012",
      "on_behalf_of_id": "party/team_daniel_gibbs_2012",
      "organization_id": "legislature",
      "person_id": "person/Q4556137",
      "role": "member"
    },
    {
      "legislative_period_id": "term/2012",
      "on_behalf_of_id": "party/rassemblement_responsabilité_réussite",
      "organization_id": "legislature",
      "person_id": "person/alain_gros-desormeaux",
      "role": "member"
    },
    {
      "legislative_period_id": "term/2012",
      "on_behalf_of_id": "party/rassemblement_responsabilité_réussite",
      "organization_id": "legislature",
      "person_id": "person/antero_santos",
      "role": "member"
    },
    {
      "legislative_period_id": "term/2012",
      "on_behalf_of_id": "party/team_daniel_gibbs_2012",
      "organization_id": "legislature",
      "person_id": "person/christophe_henocq",
      "role": "member"
    },
    {
      "legislative_period_id": "term/2012",
      "on_behalf_of_id": "party/team_daniel_gibbs_2012",
      "organization_id": "legislature",
      "person_id": "person/claire_manuel-philips",
      "role": "member"
    },
    {
      "legislative_period_id": "term/2012",
      "on_behalf_of_id": "party/team_daniel_gibbs_2012",
      "organization_id": "legislature",
      "person_id": "person/dominique_aubert",
      "role": "member"
    },
    {
      "legislative_period_id": "term/2012",
      "on_behalf_of_id": "party/rassemblement_responsabilité_réussite",
      "organization_id": "legislature",
      "person_id": "person/jean-david_richardson",
      "role": "member"
    },
    {
      "legislative_period_id": "term/2012",
      "on_behalf_of_id": "party/rassemblement_responsabilité_réussite",
      "organization_id": "legislature",
      "person_id": "person/jean-philippe_richardson",
      "role": "member"
    },
    {
      "legislative_period_id": "term/2012",
      "on_behalf_of_id": "party/rassemblement_responsabilité_réussite",
      "organization_id": "legislature",
      "person_id": "person/jeanne_rogers-vanterpool",
      "role": "member"
    },
    {
      "legislative_period_id": "term/2012",
      "on_behalf_of_id": "party/rassemblement_responsabilité_réussite",
      "organization_id": "legislature",
      "person_id": "person/josiane_carty-nettleford",
      "role": "member"
    },
    {
      "legislative_period_id": "term/2012",
      "on_behalf_of_id": "party/rassemblement_responsabilité_réussite",
      "organization_id": "legislature",
      "person_id": "person/josé_vilier",
      "role": "member"
    },
    {
      "legislative_period_id": "term/2012",
      "on_behalf_of_id": "party/team_daniel_gibbs_2012",
      "organization_id": "legislature",
      "person_id": "person/jules_charville",
      "role": "member"
    },
    {
      "legislative_period_id": "term/2012",
      "on_behalf_of_id": "party/rassemblement_responsabilité_réussite",
      "organization_id": "legislature",
      "person_id": "person/louis_fleming",
      "role": "member"
    },
    {
      "legislative_period_id": "term/2012",
      "on_behalf_of_id": "party/team_daniel_gibbs_2012",
      "organization_id": "legislature",
      "person_id": "person/maud_ascent-gibbs",
      "role": "member"
    },
    {
      "legislative_period_id": "term/2012",
      "on_behalf_of_id": "party/rassemblement_responsabilité_réussite",
      "organization_id": "legislature",
      "person_id": "person/nadine_jermin-paines",
      "role": "member"
    },
    {
      "legislative_period_id": "term/2012",
      "on_behalf_of_id": "party/rassemblement_responsabilité_réussite",
      "organization_id": "legislature",
      "person_id": "person/ramona_connor",
      "role": "member"
    },
    {
      "legislative_period_id": "term/2012",
      "on_behalf_of_id": "party/rassemblement_responsabilité_réussite",
      "organization_id": "legislature",
      "person_id": "person/rené-jean_duret",
      "role": "member"
    },
    {
      "legislative_period_id": "term/2012",
      "on_behalf_of_id": "party/rassemblement_responsabilité_réussite",
      "organization_id": "legislature",
      "person_id": "person/rolande_questel",
      "role": "member"
    },
    {
      "legislative_period_id": "term/2012",
      "on_behalf_of_id": "party/rassemblement_responsabilité_réussite",
      "organization_id": "legislature",
      "person_id": "person/rosette_gumbs-lake",
      "role": "member"
    },
    {
      "legislative_period_id": "term/2012",
      "on_behalf_of_id": "party/rassemblement_responsabilité_réussite",
      "organization_id": "legislature",
      "person_id": "person/valérie_picotin-fontrose",
      "role": "member"
    },
    {
      "legislative_period_id": "term/2012",
      "on_behalf_of_id": "party/rassemblement_responsabilité_réussite",
      "organization_id": "legislature",
      "person_id": "person/wendel_cocks",
      "role": "member"
    }
  ],
  "events": [
    {
      "classification": "legislative period",
      "id": "term/2012",
      "name": "2012–",
      "organization_id": "legislature",
      "start_date": "2012"
    }
  ],
  "areas": [

  ]
}